[
  {
    "comments": [
      {
        "line": 1,
        "value": "#language: pt"
      }
    ],
    "line": 4,
    "elements": [
      {
        "line": 10,
        "name": "",
        "description": "",
        "type": "background",
        "keyword": "Contexto",
        "steps": [
          {
            "result": {
              "duration": 4534692300,
              "status": "passed"
            },
            "line": 11,
            "name": "que desejo adicionar uma conta",
            "match": {
              "location": "InserirContasSteps.queDesejoAdicionarUmaConta()"
            },
            "keyword": "Dado "
          }
        ]
      },
      {
        "line": 19,
        "name": "Deve validar regras cadastro contas",
        "description": "",
        "id": "cadastro-de-contas;deve-validar-regras-cadastro-contas;;2",
        "after": [
          {
            "result": {
              "duration": 116043600,
              "status": "passed"
            },
            "match": {
              "location": "InserirContasSteps.screenshot(Scenario)"
            }
          },
          {
            "result": {
              "duration": 1384523600,
              "status": "passed"
            },
            "match": {
              "location": "InserirContasSteps.FecharBrowser()"
            }
          }
        ],
        "type": "scenario",
        "keyword": "Esquema do Cenário",
        "steps": [
          {
            "result": {
              "duration": 570704400,
              "status": "passed"
            },
            "line": 14,
            "name": "adiciono a conta \"Conta de Teste\"",
            "match": {
              "arguments": [
                {
                  "val": "Conta de Teste",
                  "offset": 18
                }
              ],
              "location": "InserirContasSteps.adicionoAConta(String)"
            },
            "matchedColumns": [
              0
            ],
            "keyword": "Quando "
          },
          {
            "result": {
              "duration": 40084400,
              "status": "passed"
            },
            "line": 15,
            "name": "recebo a mensagem \"Conta adicionada com sucesso!\"",
            "match": {
              "arguments": [
                {
                  "val": "Conta adicionada com sucesso!",
                  "offset": 19
                }
              ],
              "location": "InserirContasSteps.receboAMensagem(String)"
            },
            "matchedColumns": [
              1
            ],
            "keyword": "Então "
          }
        ],
        "tags": [
          {
            "line": 3,
            "name": "@funcionais"
          }
        ]
      },
      {
        "line": 10,
        "name": "",
        "description": "",
        "type": "background",
        "keyword": "Contexto",
        "steps": [
          {
            "result": {
              "duration": 4519436200,
              "status": "passed"
            },
            "line": 11,
            "name": "que desejo adicionar uma conta",
            "match": {
              "location": "InserirContasSteps.queDesejoAdicionarUmaConta()"
            },
            "keyword": "Dado "
          }
        ]
      },
      {
        "line": 20,
        "name": "Deve validar regras cadastro contas",
        "description": "",
        "id": "cadastro-de-contas;deve-validar-regras-cadastro-contas;;3",
        "after": [
          {
            "result": {
              "duration": 88838200,
              "status": "passed"
            },
            "match": {
              "location": "InserirContasSteps.screenshot(Scenario)"
            }
          },
          {
            "result": {
              "duration": 1381081500,
              "status": "passed"
            },
            "match": {
              "location": "InserirContasSteps.FecharBrowser()"
            }
          }
        ],
        "type": "scenario",
        "keyword": "Esquema do Cenário",
        "steps": [
          {
            "result": {
              "duration": 619918200,
              "status": "passed"
            },
            "line": 14,
            "name": "adiciono a conta \"\"",
            "match": {
              "arguments": [
                {
                  "val": "",
                  "offset": 18
                }
              ],
              "location": "InserirContasSteps.adicionoAConta(String)"
            },
            "matchedColumns": [
              0
            ],
            "keyword": "Quando "
          },
          {
            "result": {
              "duration": 68355900,
              "status": "passed"
            },
            "line": 15,
            "name": "recebo a mensagem \"Informe o nome da conta\"",
            "match": {
              "arguments": [
                {
                  "val": "Informe o nome da conta",
                  "offset": 19
                }
              ],
              "location": "InserirContasSteps.receboAMensagem(String)"
            },
            "matchedColumns": [
              1
            ],
            "keyword": "Então "
          }
        ],
        "tags": [
          {
            "line": 3,
            "name": "@funcionais"
          }
        ]
      },
      {
        "line": 10,
        "name": "",
        "description": "",
        "type": "background",
        "keyword": "Contexto",
        "steps": [
          {
            "result": {
              "duration": 4723586800,
              "status": "passed"
            },
            "line": 11,
            "name": "que desejo adicionar uma conta",
            "match": {
              "location": "InserirContasSteps.queDesejoAdicionarUmaConta()"
            },
            "keyword": "Dado "
          }
        ]
      },
      {
        "line": 21,
        "name": "Deve validar regras cadastro contas",
        "description": "",
        "id": "cadastro-de-contas;deve-validar-regras-cadastro-contas;;4",
        "after": [
          {
            "result": {
              "duration": 89492000,
              "status": "passed"
            },
            "match": {
              "location": "InserirContasSteps.screenshot(Scenario)"
            }
          },
          {
            "result": {
              "duration": 1110745600,
              "status": "passed"
            },
            "match": {
              "location": "InserirContasSteps.FecharBrowser()"
            }
          }
        ],
        "type": "scenario",
        "keyword": "Esquema do Cenário",
        "steps": [
          {
            "result": {
              "duration": 408750000,
              "status": "passed"
            },
            "line": 14,
            "name": "adiciono a conta \"Conta mesmo nome\"",
            "match": {
              "arguments": [
                {
                  "val": "Conta mesmo nome",
                  "offset": 18
                }
              ],
              "location": "InserirContasSteps.adicionoAConta(String)"
            },
            "matchedColumns": [
              0
            ],
            "keyword": "Quando "
          },
          {
            "result": {
              "duration": 49528500,
              "status": "passed"
            },
            "line": 15,
            "name": "recebo a mensagem \"Já existe uma conta com esse nome!\"",
            "match": {
              "arguments": [
                {
                  "val": "Já existe uma conta com esse nome!",
                  "offset": 19
                }
              ],
              "location": "InserirContasSteps.receboAMensagem(String)"
            },
            "matchedColumns": [
              1
            ],
            "keyword": "Então "
          }
        ],
        "tags": [
          {
            "line": 3,
            "name": "@funcionais"
          }
        ]
      }
    ],
    "name": "Cadastro de contas",
    "description": "\r\nComo um usuário \r\nGostaria de cadastrar contas\r\nPara que eu possa distribuir meu dinheiro de uma forma mais organizada",
    "id": "cadastro-de-contas",
    "keyword": "Funcionalidade",
    "uri": "inserir_conta.feature",
    "tags": [
      {
        "line": 3,
        "name": "@funcionais"
      }
    ]
  }
]